api_farm/__init__.py
api_farm/__main__.py
api_farm/cli.py
api_farm/client_sdk.py
api_farm/server.py
api_farm-0.1.0.1.dist-info/licenses/LICENSE
api_farm-0.1.0.1.dist-info/METADATA
api_farm-0.1.0.1.dist-info/WHEEL
api_farm-0.1.0.1.dist-info/entry_points.txt
api_farm-0.1.0.1.dist-info/top_level.txt
api_farm-0.1.0.1.dist-info/RECORD
