Metadata-Version: 2.4
Name: api_farm
Version: 0.1.0.1
Summary: A shared API key pool server and client for managing and using API keys
Author: API Farm Team
Project-URL: Homepage, https://github.com/zhusq20/APIFarm.git
Classifier: Programming Language :: Python :: 3
Classifier: Programming Language :: Python :: 3.8
Classifier: Programming Language :: Python :: 3.9
Classifier: Programming Language :: Python :: 3.10
Classifier: Programming Language :: Python :: 3.11
Classifier: License :: OSI Approved :: MIT License
Classifier: Operating System :: OS Independent
Requires-Python: >=3.8
License-File: LICENSE
Requires-Dist: nest_asyncio
Requires-Dist: fastapi
Requires-Dist: httpx
Requires-Dist: uvicorn
Requires-Dist: openai
Requires-Dist: pytest-asyncio
Requires-Dist: tqdm
Dynamic: license-file
